facile/.gitignore
facile/__init__.py
facile/core.cpython-311-x86_64-linux-gnu.so
facile/core.pyi
facile/core.pyx
facile-1.6.dist-info/WHEEL
facile-1.6.dist-info/METADATA
facile-1.6.dist-info/RECORD
