Metadata-Version: 2.1
Name: facile
Version: 1.6
Summary: Python constraint programming library
Home-page: https://github.com/xoolive/facile
License: LGPL 3.0
Author: Xavier Olive
Author-email: git@xoolive.org
Requires-Python: >=3.8,<4.0
Classifier: License :: Other/Proprietary License
Classifier: Programming Language :: Python :: 3
Classifier: Programming Language :: Python :: 3.10
Classifier: Programming Language :: Python :: 3.8
Classifier: Programming Language :: Python :: 3.9
Requires-Dist: importlib-metadata (>=4.6.1,<5.0.0)
